quarto_tech_memo/quarto_tech_memo.py
quarto_tech_memo-0.3.0.dist-info/licenses/LICENSE
quarto_tech_memo-0.3.0.dist-info/METADATA
quarto_tech_memo-0.3.0.dist-info/WHEEL
quarto_tech_memo-0.3.0.dist-info/entry_points.txt
quarto_tech_memo-0.3.0.dist-info/top_level.txt
quarto_tech_memo-0.3.0.dist-info/RECORD
