Metadata-Version: 2.4
Name: quarto-tech-memo
Version: 0.3.0
Summary: A CLI script to convert a markdown note to a polished PDF tech memo using Quarto.
Author-email: Gaël Close <closega@gmail.com>
License: MIT License
Project-URL: Source, https://github.com/gael-close/quarto-tech-memo
Requires-Python: >=3.8
License-File: LICENSE
Requires-Dist: quarto-cli
Requires-Dist: typer
Dynamic: license-file
